dbd_music/__init__.py
dbd_music/__main__.py
dbd_music-0.0.6.dist-info/METADATA
dbd_music-0.0.6.dist-info/WHEEL
dbd_music-0.0.6.dist-info/top_level.txt
dbd_music-0.0.6.dist-info/RECORD
